<?xml version="1.0" encoding="utf-8"?>
<search>
  
  
  
  <entry>
    <title>信号与系统公式总结</title>
    <link href="/2022/06/06/%E4%BF%A1%E5%8F%B7%E4%B8%8E%E7%B3%BB%E7%BB%9F%E5%85%AC%E5%BC%8F%E6%80%BB%E7%BB%93/"/>
    <url>/2022/06/06/%E4%BF%A1%E5%8F%B7%E4%B8%8E%E7%B3%BB%E7%BB%9F%E5%85%AC%E5%BC%8F%E6%80%BB%E7%BB%93/</url>
    
    <content type="html"><![CDATA[<p>傅里叶变换的性质：<br>1.线性：若f(t)⇄F(jω),则有a1f1(t)+a2f2(t)⇄a1F1(jω)+a2F2(jω).<br>2.对称性：若f(t)⇄F(jω),则有F(jt)⇄2πf(-ω).<br>3.尺度变换：若f(t)⇄F(jω),则有f(at)⇄1&#x2F;|a|F(jω&#x2F;a).<br>4.时移特性：若f(t)⇄F(jω),则有f(t±t0)⇄e^±jωt0F(jω).<br>5.频移特性：若f(t)⇄F(jω),则有e^∓jω0tf(t)⇄F[j(ω±ω0)].<br>6.时域微分：若f(t)⇄F(jω),则有f^n(t)⇄jω^nF(jω).<br>7.时域积分：若f(t)⇄F(jω),则有f-1(t)⇄πF(0)δ(ω)+F(jω)&#x2F;jω.<br>8.频域微分：若f(t)⇄F(jω),则有-jt^nf(t)⇄F^n(jω).<br>9.频域积分：若f(t)⇄F(jω),则有πf(0)δ(t)+f(t)&#x2F;-jt⇄F-1(jω).</p><p>拉普拉斯变换的性质：<br>1.线性：对于单边变换,若f(t)⇄F(s),则有a1f1(t)+a2f2(t)⇄a1F1(s)+a2F2(s).[σ&gt;max(σ1,σ2)];对于双边变换,若f(t)⇄F(s),则有a1f1(t)+a2f2(t)⇄a1Fb1(s)+a2Fb2(s).[max(α1,α2)&lt;σ&lt;max(β1,β2)]<br>2.尺度变换：对于单边变换,若f(t)⇄F(s),则有f(at)⇄1&#x2F;aF(s&#x2F;a)[σ&gt;aσ0];对于双边变换,若f(t)⇄F(s),则有f(at)⇄1&#x2F;|a|Fb(s&#x2F;a).[σ&gt;aσ0]<br>3.时移特性：对于单边变换,若f(t)⇄F(s),则有f(t-t0)ε(t-t0)⇄e^-st0F(s)[σ&gt;σ0];对于双边变换,若f(t)⇄F(s),则有f(t-t0)⇄e^-st0Fb(s).[α&lt;σ&lt;β]<br>4.复频移特性：对于单边变换,若f(t)⇄F(s),则有f(t)e^sa<em>t⇄F(s-sa)[σ&gt;σ0+σa];对于双边变换,若f(t)⇄F(s),则有e^-sa</em>tf(t)⇄Fb(s+sa).[α-Re[sa]&lt;σ&lt;β-Re[sa]]<br>5.时域微分：对于单边变换,若f(t)⇄F(s),则有f(1)(t)⇄sF(s)-f(0-)[σ&gt;σ0];对于双边变换,若f(t)⇄F(s),则有df(t)&#x2F;dt⇄sFb(s).[α&lt;σ&lt;β]<br>6.时域积分：对于单边变换,若f(t)⇄F(s),则有f(-)(t)⇄1&#x2F;sF(s)+1&#x2F;s*f(-1)(0-);对于双边变换,若f(t)⇄F(s),则有∫(-∞→t) f(x)dx⇄1&#x2F;sFb(s).[max(α,0)&lt;σ&lt;β]</p>]]></content>
    
    
    
  </entry>
  
  
  
  <entry>
    <title>linguistics</title>
    <link href="/2022/05/21/linguistics/"/>
    <url>/2022/05/21/linguistics/</url>
    
    <content type="html"><![CDATA[<p>Linguistics,the science of language,or the scientific study of language,is an essential research field for both the development of individuals and whole society.People can not communicate without language,and the means of performing language is critical in speech therapy,education,translation and many other practical sectors.For this reason,linguistics is bound to be an academically and economically favored pursuit.<br>Moreover,it has become an academic area with immense research potential,and a scholarly industry which produces a large amount of books,dissertations and papers every year,its preoccupations are also expressed in many specialized journals as Language, Journal of Linguistics, Lingua, Applied Linguistics etc. and at regular conferences.In China the study of language has a long history but contemporary linguistics still has a long way to go to reach its peak.So,as students in the new age,we should be aware of the importance of learning linguistics and explore it actively and continuously to make a difference to human society.</p>]]></content>
    
    
    
  </entry>
  
  
  
  <entry>
    <title>Hello World</title>
    <link href="/2022/05/21/hello-world/"/>
    <url>/2022/05/21/hello-world/</url>
    
    <content type="html"><![CDATA[<p>Welcome to <a href="https://hexo.io/">Hexo</a>! This is your very first post. Check <a href="https://hexo.io/docs/">documentation</a> for more info. If you get any problems when using Hexo, you can find the answer in <a href="https://hexo.io/docs/troubleshooting.html">troubleshooting</a> or you can ask me on <a href="https://github.com/hexojs/hexo/issues">GitHub</a>.</p><h2 id="Quick-Start"><a href="#Quick-Start" class="headerlink" title="Quick Start"></a>Quick Start</h2><h3 id="Create-a-new-post"><a href="#Create-a-new-post" class="headerlink" title="Create a new post"></a>Create a new post</h3><figure class="highlight bash"><table><tr><td class="gutter"><pre><span class="line">1</span><br></pre></td><td class="code"><pre><span class="line">$ hexo new <span class="string">&quot;My New Post&quot;</span></span><br></pre></td></tr></table></figure><p>More info: <a href="https://hexo.io/docs/writing.html">Writing</a></p><h3 id="Run-server"><a href="#Run-server" class="headerlink" title="Run server"></a>Run server</h3><figure class="highlight bash"><table><tr><td class="gutter"><pre><span class="line">1</span><br></pre></td><td class="code"><pre><span class="line">$ hexo server</span><br></pre></td></tr></table></figure><p>More info: <a href="https://hexo.io/docs/server.html">Server</a></p><h3 id="Generate-static-files"><a href="#Generate-static-files" class="headerlink" title="Generate static files"></a>Generate static files</h3><figure class="highlight bash"><table><tr><td class="gutter"><pre><span class="line">1</span><br></pre></td><td class="code"><pre><span class="line">$ hexo generate</span><br></pre></td></tr></table></figure><p>More info: <a href="https://hexo.io/docs/generating.html">Generating</a></p><h3 id="Deploy-to-remote-sites"><a href="#Deploy-to-remote-sites" class="headerlink" title="Deploy to remote sites"></a>Deploy to remote sites</h3><figure class="highlight bash"><table><tr><td class="gutter"><pre><span class="line">1</span><br></pre></td><td class="code"><pre><span class="line">$ hexo deploy</span><br></pre></td></tr></table></figure><p>More info: <a href="https://hexo.io/docs/one-command-deployment.html">Deployment</a></p>]]></content>
    
    
    
  </entry>
  
  
  
  
</search>
